{"cameraMode":{"drawMode":0,"name":"Shaded","section":"Shading Mode"},"sceneLighting":true,"audioPlay":false,"sceneViewState":{"showFog":true,"showMaterialUpdate":false,"showSkybox":true,"showFlares":true,"showImageEffects":true,"showParticleSystems":true},"in2DMode":false,"pivot":{"x":-0.2736817002296448,"y":-1.6323094367980958,"z":-24.697664260864259},"rotation":{"x":-0.001393224229104817,"y":-0.9870592951774597,"z":0.16011889278888703,"w":-0.008599737659096718},"size":22.0,"orthographic":false}